associations/__init__.py
associations-0.0.4.dist-info/LICENSE
associations-0.0.4.dist-info/METADATA
associations-0.0.4.dist-info/WHEEL
associations-0.0.4.dist-info/top_level.txt
associations-0.0.4.dist-info/RECORD
