Metadata-Version: 2.1
Name: associations
Version: 0.0.4
Summary: Assocition management package
Home-page: https://github.com/pypa/associations
Author: Hyppoprogramm
Author-email: programm.jeremiah@yandex.ru
License: UNKNOWN
Platform: UNKNOWN
Classifier: Programming Language :: Python :: 3
Classifier: License :: OSI Approved :: MIT License
Classifier: Operating System :: OS Independent
Requires-Python: >=3.6
